<?xml version="1.0" encoding="UTF-8"?><record_update sys_domain="global" table="sys_hub_action_type_definition">
    <sys_hub_action_type_definition action="DELETE">
        <access>public</access>
        <acls/>
        <action_status/>
        <action_template/>
        <active>true</active>
        <annotation/>
        <attributes>{labelCacheCleanUpExecuted=true}</attributes>
        <authored_on_release_version>26000</authored_on_release_version>
        <callable_by_client_api>false</callable_by_client_api>
        <category display_value="">{}</category>
        <compiler_build/>
        <copied_from/>
        <copied_from_name/>
        <description/>
        <flow_priority/>
        <ih_action>false</ih_action>
        <internal_name>create_system_record</internal_name>
        <label_cache/>
        <latest_snapshot/>
        <master_snapshot/>
        <master_snapshot_digest/>
        <name>Create System Record</name>
        <natlang/>
        <outputs/>
        <pre_compiled>false</pre_compiled>
        <state>draft</state>
        <sys_class_name>sys_hub_action_type_definition</sys_class_name>
        <sys_created_by>john.spirko</sys_created_by>
        <sys_created_on>2024-09-04 23:43:24</sys_created_on>
        <sys_domain>global</sys_domain>
        <sys_id>af03244087241a9099eab88c8bbb3572</sys_id>
        <sys_mod_count>0</sys_mod_count>
        <sys_name>Create System Record</sys_name>
        <sys_overrides/>
        <sys_package display_value="15-Minute Digital Product Prototype" source="x_snc_15_minute_se">9c753ca0479902504f6574fc416d43d9</sys_package>
        <sys_policy/>
        <sys_scope display_value="15-Minute Digital Product Prototype">9c753ca0479902504f6574fc416d43d9</sys_scope>
        <sys_update_name>sys_hub_action_type_definition_af03244087241a9099eab88c8bbb3572</sys_update_name>
        <sys_updated_by>john.spirko</sys_updated_by>
        <sys_updated_on>2024-09-04 23:43:24</sys_updated_on>
        <system_level>false</system_level>
        <type/>
    </sys_hub_action_type_definition>
    <sys_variable_value action="DELETE" query="document_key=af03244087241a9099eab88c8bbb3572"/>
    <sys_hub_step_instance action="DELETE" query="action=af03244087241a9099eab88c8bbb3572"/>
    <sys_hub_action_input action="DELETE" query="model=af03244087241a9099eab88c8bbb3572"/>
    <sys_hub_action_output action="DELETE" query="model=af03244087241a9099eab88c8bbb3572"/>
    <sys_hub_pill_compound action="DELETE" query="attached_to=af03244087241a9099eab88c8bbb3572"/>
    <sys_hub_action_status_metadata action="DELETE" query="action_type_id=af03244087241a9099eab88c8bbb3572"/>
    <sys_documentation action="DELETE" query="name=var__m_sys_hub_action_input_af03244087241a9099eab88c8bbb3572"/>
    <sys_choice action="DELETE" query="name=var__m_sys_hub_action_input_af03244087241a9099eab88c8bbb3572"/>
    <sys_documentation action="DELETE" query="name=var__m_sys_hub_action_output_af03244087241a9099eab88c8bbb3572"/>
    <sys_choice action="DELETE" query="name=var__m_sys_hub_action_output_af03244087241a9099eab88c8bbb3572"/>
    <sys_hub_action_plan action="DELETE" query="action_id=af03244087241a9099eab88c8bbb3572"/>
    <sys_update_version action="INSERT_OR_UPDATE">
        <action>DELETE</action>
        <application display_value="15-Minute Digital Product Prototype">9c753ca0479902504f6574fc416d43d9</application>
        <file_path/>
        <instance_id>efeaa946dbc0c740b2e05d00cf96194a</instance_id>
        <instance_name>empjspirkosc2</instance_name>
        <name>sys_hub_action_type_definition_af03244087241a9099eab88c8bbb3572</name>
        <payload><![CDATA[<?xml version="1.0" encoding="UTF-8"?><record_update sys_domain="global" table="sys_hub_action_type_definition"><sys_hub_action_type_definition action="INSERT_OR_UPDATE"><access>public</access><acls/><action_status/><action_template/><active>true</active><annotation/><attributes>{labelCacheCleanUpExecuted=true}</attributes><authored_on_release_version>26000</authored_on_release_version><callable_by_client_api>false</callable_by_client_api><category display_value="">{}</category><compiler_build/><copied_from/><copied_from_name/><description/><flow_priority/><ih_action>false</ih_action><internal_name>create_system_record</internal_name><label_cache/><latest_snapshot/><master_snapshot/><master_snapshot_digest/><name>Create System Record</name><natlang/><outputs/><pre_compiled>false</pre_compiled><state>draft</state><sys_class_name>sys_hub_action_type_definition</sys_class_name><sys_created_by>john.spirko</sys_created_by><sys_created_on>2024-09-04 23:43:24</sys_created_on><sys_domain>global</sys_domain><sys_id>af03244087241a9099eab88c8bbb3572</sys_id><sys_mod_count>0</sys_mod_count><sys_name>Create System Record</sys_name><sys_overrides/><sys_package display_value="15-Minute Digital Product Prototype" source="x_snc_15_minute_se">9c753ca0479902504f6574fc416d43d9</sys_package><sys_policy/><sys_scope display_value="15-Minute Digital Product Prototype">9c753ca0479902504f6574fc416d43d9</sys_scope><sys_update_name>sys_hub_action_type_definition_af03244087241a9099eab88c8bbb3572</sys_update_name><sys_updated_by>john.spirko</sys_updated_by><sys_updated_on>2024-09-04 23:43:24</sys_updated_on><system_level>false</system_level><type/></sys_hub_action_type_definition><sys_variable_value action="delete_multiple" query="document_key=af03244087241a9099eab88c8bbb3572"/><sys_hub_step_instance action="delete_multiple" query="action=af03244087241a9099eab88c8bbb3572"/><sys_hub_action_input action="delete_multiple" query="model=af03244087241a9099eab88c8bbb3572"/><sys_hub_action_output action="delete_multiple" query="model=af03244087241a9099eab88c8bbb3572"/><sys_hub_pill_compound action="delete_multiple" query="attached_to=af03244087241a9099eab88c8bbb3572"/><sys_hub_action_status_metadata action="delete_multiple" query="action_type_id=af03244087241a9099eab88c8bbb3572"/><sys_documentation action="delete_multiple" query="name=var__m_sys_hub_action_input_af03244087241a9099eab88c8bbb3572"/><sys_choice action="delete_multiple" query="name=var__m_sys_hub_action_input_af03244087241a9099eab88c8bbb3572"/><sys_documentation action="delete_multiple" query="name=var__m_sys_hub_action_output_af03244087241a9099eab88c8bbb3572"/><sys_choice action="delete_multiple" query="name=var__m_sys_hub_action_output_af03244087241a9099eab88c8bbb3572"/><sys_hub_action_plan action="delete_multiple" query="action_id=af03244087241a9099eab88c8bbb3572"/></record_update>]]></payload>
        <payload_hash>-1788933953</payload_hash>
        <record_name>Create System Record</record_name>
        <reverted_from/>
        <source>52c1240c872cd69099eab88c8bbb3538</source>
        <source_table>sys_update_set</source_table>
        <state>current</state>
        <sys_created_by>john.spirko</sys_created_by>
        <sys_created_on>2024-09-04 23:43:24</sys_created_on>
        <sys_id>2703244087241a9099eab88c8bbb3578</sys_id>
        <sys_mod_count>0</sys_mod_count>
        <sys_recorded_at>191bf6be2e20000001</sys_recorded_at>
        <sys_updated_by>john.spirko</sys_updated_by>
        <sys_updated_on>2024-09-04 23:43:24</sys_updated_on>
        <type>Action Type</type>
        <update_guid>e703244056241a9070c38e18fef3fb77</update_guid>
        <update_guid_history>e703244056241a9070c38e18fef3fb77:-1788933953</update_guid_history>
    </sys_update_version>
    <sys_metadata_delete action="INSERT_OR_UPDATE">
        <sys_audit_delete/>
        <sys_class_name>sys_metadata_delete</sys_class_name>
        <sys_created_by>john.spirko</sys_created_by>
        <sys_created_on>2024-10-12 20:54:21</sys_created_on>
        <sys_db_object display_value="" name="sys_hub_action_type_definition">sys_hub_action_type_definition</sys_db_object>
        <sys_id>5715cfbc8a264a1a8b6475fc8942ac29</sys_id>
        <sys_metadata>af03244087241a9099eab88c8bbb3572</sys_metadata>
        <sys_mod_count>0</sys_mod_count>
        <sys_name>Create System Record</sys_name>
        <sys_package display_value="15-Minute Digital Product Prototype" source="x_snc_15_minute_se">9c753ca0479902504f6574fc416d43d9</sys_package>
        <sys_parent/>
        <sys_policy/>
        <sys_scope display_value="15-Minute Digital Product Prototype">9c753ca0479902504f6574fc416d43d9</sys_scope>
        <sys_scope_delete display_value="">230f96bf0ff44c9496c73d4227f02fc1</sys_scope_delete>
        <sys_update_name>sys_hub_action_type_definition_af03244087241a9099eab88c8bbb3572</sys_update_name>
        <sys_update_version display_value="sys_hub_action_type_definition_af03244087241a9099eab88c8bbb3572">2703244087241a9099eab88c8bbb3578</sys_update_version>
        <sys_updated_by>john.spirko</sys_updated_by>
        <sys_updated_on>2024-10-12 20:54:21</sys_updated_on>
    </sys_metadata_delete>
</record_update>
