<?xml version="1.0" encoding="UTF-8"?><record_update sys_domain="global" table="sys_app_application">
    <sys_app_application action="DELETE">
        <active>true</active>
        <category display_value="Custom Applications">e0355b31ef303000a61d5a3615c0fb78</category>
        <description/>
        <device_type>browser</device_type>
        <hint/>
        <name>demo</name>
        <order>100</order>
        <roles>x_snc_15_minute_se.demo_user</roles>
        <sys_class_name>sys_app_application</sys_class_name>
        <sys_created_by>jspirko</sys_created_by>
        <sys_created_on>2024-03-31 21:45:30</sys_created_on>
        <sys_domain>global</sys_domain>
        <sys_domain_path>/</sys_domain_path>
        <sys_id>0276e75d471d46504f6574fc416d43df</sys_id>
        <sys_mod_count>0</sys_mod_count>
        <sys_name>demo</sys_name>
        <sys_overrides/>
        <sys_package display_value="15-Minute Service MVP" source="x_snc_15_minute_se">9c753ca0479902504f6574fc416d43d9</sys_package>
        <sys_policy/>
        <sys_scope display_value="15-Minute Service MVP">9c753ca0479902504f6574fc416d43d9</sys_scope>
        <sys_update_name>sys_app_application_0276e75d471d46504f6574fc416d43df</sys_update_name>
        <sys_updated_by>jspirko</sys_updated_by>
        <sys_updated_on>2024-03-31 21:45:30</sys_updated_on>
        <title>demo</title>
        <view_name/>
    </sys_app_application>
    <sys_update_version action="INSERT_OR_UPDATE">
        <action>DELETE</action>
        <application display_value="15-Minute Digital Product Prototype">9c753ca0479902504f6574fc416d43d9</application>
        <file_path/>
        <instance_id>76bfb9f61ba9f594fe1b43f4bd4bcb74</instance_id>
        <instance_name>dsforum</instance_name>
        <name>sys_app_application_0276e75d471d46504f6574fc416d43df</name>
        <payload><![CDATA[<?xml version="1.0" encoding="UTF-8"?><record_update sys_domain="global" table="sys_app_application"><sys_app_application action="INSERT_OR_UPDATE"><active>true</active><category display_value="Custom Applications">e0355b31ef303000a61d5a3615c0fb78</category><description/><device_type>browser</device_type><hint/><name>demo</name><order>100</order><roles>x_snc_15_minute_se.demo_user</roles><sys_class_name>sys_app_application</sys_class_name><sys_created_by>jspirko</sys_created_by><sys_created_on>2024-03-31 21:45:30</sys_created_on><sys_domain>global</sys_domain><sys_domain_path>/</sys_domain_path><sys_id>0276e75d471d46504f6574fc416d43df</sys_id><sys_mod_count>0</sys_mod_count><sys_name>demo</sys_name><sys_overrides/><sys_package display_value="15-Minute Service MVP" source="x_snc_15_minute_se">9c753ca0479902504f6574fc416d43d9</sys_package><sys_policy/><sys_scope display_value="15-Minute Service MVP">9c753ca0479902504f6574fc416d43d9</sys_scope><sys_update_name>sys_app_application_0276e75d471d46504f6574fc416d43df</sys_update_name><sys_updated_by>jspirko</sys_updated_by><sys_updated_on>2024-03-31 21:45:30</sys_updated_on><title>demo</title><view_name/></sys_app_application></record_update>]]></payload>
        <payload_hash>1362298753</payload_hash>
        <record_name>demo</record_name>
        <reverted_from/>
        <source>d0753ca0479902504f6574fc416d43de</source>
        <source_table>sys_update_set</source_table>
        <state>previous</state>
        <sys_created_by>jspirko</sys_created_by>
        <sys_created_on>2024-03-31 21:45:31</sys_created_on>
        <sys_id>92762b5d471d46504f6574fc416d43e7</sys_id>
        <sys_mod_count>0</sys_mod_count>
        <sys_recorded_at>18e9679887a0000001</sys_recorded_at>
        <sys_updated_by>jspirko</sys_updated_by>
        <sys_updated_on>2024-03-31 21:45:31</sys_updated_on>
        <type>Application Menu</type>
        <update_guid>86762b5d931d465006d1efd80f9f27e6</update_guid>
        <update_guid_history>86762b5d931d465006d1efd80f9f27e6:1362298753</update_guid_history>
    </sys_update_version>
    <sys_metadata_delete action="INSERT_OR_UPDATE">
        <sys_audit_delete display_value="demo">0f2f90a5479186504f6574fc416d432a</sys_audit_delete>
        <sys_class_name>sys_metadata_delete</sys_class_name>
        <sys_created_by>admin</sys_created_by>
        <sys_created_on>2024-04-01 01:53:14</sys_created_on>
        <sys_db_object display_value="" name="sys_app_application">sys_app_application</sys_db_object>
        <sys_id>24565422a41341ee800d8f17e4720984</sys_id>
        <sys_metadata>0276e75d471d46504f6574fc416d43df</sys_metadata>
        <sys_mod_count>0</sys_mod_count>
        <sys_name>demo</sys_name>
        <sys_package display_value="15-Minute Digital Product Prototype" source="x_snc_15_minute_se">9c753ca0479902504f6574fc416d43d9</sys_package>
        <sys_parent/>
        <sys_policy/>
        <sys_scope display_value="15-Minute Digital Product Prototype">9c753ca0479902504f6574fc416d43d9</sys_scope>
        <sys_scope_delete display_value="">230f96bf0ff44c9496c73d4227f02fc1</sys_scope_delete>
        <sys_update_name>sys_app_application_0276e75d471d46504f6574fc416d43df</sys_update_name>
        <sys_update_version display_value="sys_app_application_0276e75d471d46504f6574fc416d43df">92762b5d471d46504f6574fc416d43e7</sys_update_version>
        <sys_updated_by>admin</sys_updated_by>
        <sys_updated_on>2024-04-01 01:53:14</sys_updated_on>
    </sys_metadata_delete>
</record_update>
